Metadata-Version: 2.4
Name: etl-utilities-ameijin
Version: 1.0.3
Summary: This repository is forked from etl-utilities.
Project-URL: Documentation, https://github.com/ameijin/etl_utilities#readme
Project-URL: Issues, https://github.com/ameijin/etl_utilities/issues
Project-URL: Source, https://github.com/ameijin/etl_utilities
Author-email: Eiji <eiji@eidosoft.co>
License-Expression: MIT
License-File: LICENSE
Keywords: cleaning,database,dataframe,etl,etl-utilities,pandas,utilities
Classifier: Development Status :: 4 - Beta
Classifier: Programming Language :: Python
Classifier: Programming Language :: Python :: 3.8
Classifier: Programming Language :: Python :: 3.9
Classifier: Programming Language :: Python :: 3.10
Classifier: Programming Language :: Python :: 3.11
Classifier: Programming Language :: Python :: 3.12
Classifier: Programming Language :: Python :: 3.13
Classifier: Programming Language :: Python :: Implementation :: CPython
Classifier: Programming Language :: Python :: Implementation :: PyPy
Requires-Python: >=3.8
Requires-Dist: numpy
Requires-Dist: pandas
Requires-Dist: psycopg2-binary
Requires-Dist: python-dateutil
Requires-Dist: rich
Requires-Dist: sqlalchemy
